MANIFEST.in
pynhost.ini
setup.py
pynhost/__init__.py
pynhost/api.py
pynhost/commands.py
pynhost/configmenu.py
pynhost/constants.py
pynhost/dynamic.py
pynhost/engineio.py
pynhost/grammarbase.py
pynhost/grammarhandler.py
pynhost/history.py
pynhost/keyinput.py
pynhost/matching.py
pynhost/regex_range.py
pynhost/ruleparser.py
pynhost/utilities.py
pynhost.egg-info/PKG-INFO
pynhost.egg-info/SOURCES.txt
pynhost.egg-info/dependency_links.txt
pynhost.egg-info/top_level.txt
scripts/pynacea.py