Metadata-Version: 1.1
Name: pynhost
Version: 0.5.0
Summary: Linux Voice Recognition System
Home-page: https://github.com/evfredericksen/pynacea
Author: Evan Fredericksen
Author-email: evfredericksen@gmail.com
License: MIT
Keywords: voice recognition grammar
Platform: UNKNOWN
Classifier: Development Status :: 3 - Alpha
Classifier: Intended Audience :: Developers
Classifier: Topic :: Software Development :: Build Tools
Classifier: License :: OSI Approved :: MIT License
Classifier: Programming Language :: Python :: 3
Classifier: Programming Language :: Python :: 3.2
Classifier: Programming Language :: Python :: 3.3
Classifier: Programming Language :: Python :: 3.4
